stts22h.py
circuitpython_stts22h-0.1.1.dist-info/LICENSE
circuitpython_stts22h-0.1.1.dist-info/METADATA
circuitpython_stts22h-0.1.1.dist-info/WHEEL
circuitpython_stts22h-0.1.1.dist-info/top_level.txt
circuitpython_stts22h-0.1.1.dist-info/RECORD
