Metadata-Version: 2.1
Name: circuitpython-stts22h
Version: 0.1.1
Summary: CircuitPython Driver for the STTS22H Temperature Sensor
Author-email: "Jose D. Montoya" <jlib@mailmeto.mozmail.com>
License: MIT
Project-URL: Homepage, https://github.com/jposada202020/CircuitPython_STTS22H
Keywords: sensor,blinka,circuitpython,micropython,stts22h,temperature,sensor,STTS22H,driver
Classifier: Intended Audience :: Developers
Classifier: Topic :: Software Development :: Libraries
Classifier: Topic :: Software Development :: Embedded Systems
Classifier: Topic :: System :: Hardware
Classifier: License :: OSI Approved :: MIT License
Classifier: Programming Language :: Python :: 3
License-File: LICENSE
Requires-Dist: Adafruit-Blinka
Requires-Dist: adafruit-circuitpython-busdevice
Requires-Dist: adafruit-circuitpython-register
Provides-Extra: optional
